dssp_wsl/__init__.py
dssp_wsl-0.1.1.dist-info/LICENSE
dssp_wsl-0.1.1.dist-info/METADATA
dssp_wsl-0.1.1.dist-info/WHEEL
dssp_wsl-0.1.1.dist-info/entry_points.txt
dssp_wsl-0.1.1.dist-info/top_level.txt
dssp_wsl-0.1.1.dist-info/RECORD
